[
  {
    "Week":0,
    "Par":36,
    "Date":"4/23/2022",
    "Course":"Silver Front"
  },
  {
    "Week":1,
    "Par":36,
    "Date":"4/29/2022",
    "Course":"Silver Front"
  },
  {
    "Week":2,
    "Par":37,
    "Date":"5/6/2022",
    "Course":"Silver Back"
  },
  {
    "Week":3,
    "Par":36,
    "Date":"5/13/2022",
    "Course":"Gold Front"
  },
  {
    "Week":4,
    "Par":36,
    "Date":"5/20/2022",
    "Course":"Gold Back"
  },
  {
    "Week":5,
    "Par":36,
    "Date":"6/3/2022",
    "Course":"Silver Front"
  },
  {
    "Week":6,
    "Par":37,
    "Date":"6/10/2022",
    "Course":"Silver Back"
  },
  {
    "Week":7,
    "Par":36,
    "Date":"6/17/2022",
    "Course":"Gold Front"
  },
  {
    "Week":8,
    "Par":36,
    "Date":"6/24/2022",
    "Course":"Gold Back"
  },
  {
    "Week":9,
    "Par":37,
    "Date":"7/8/2022",
    "Course":"Silver Back"
  },
  {
    "Week":10,
    "Par":36,
    "Date":"7/15/2022",
    "Course":"Gold Front"
  },
  {
    "Week":11,
    "Par":36,
    "Date":"7/22/2022",
    "Course":"Gold Back"
  },
  {
    "Week":12,
    "Par":36,
    "Date":"7/29/2022",
    "Course":"Silver Front"
  },
  {
    "Week":13,
    "Par":37,
    "Date":"8/5/2022",
    "Course":"Silver Back"
  },
  {
    "Week":14,
    "Par":36,
    "Date":"8/12/2022",
    "Course":"Gold Front"
  },
  {
    "Week":15,
    "Par":36,
    "Date":"8/19/2022",
    "Course":"Gold Back"
  },
  {
    "Week":16,
    "Par":36,
    "Date":"8/26/2022",
    "Course":"Silver Front"
  },
  {
    "Week":17,
    "Par":37,
    "Date":"9/9/2022",
    "Course":"Silver Back"
  }
]